dfa_visualization/__init__.py
dfa_visualization/app.py
dfa_visualization/nfa.py
DFA_visual_demo-1.0.3.dist-info/LICENCE.txt
DFA_visual_demo-1.0.3.dist-info/METADATA
DFA_visual_demo-1.0.3.dist-info/WHEEL
DFA_visual_demo-1.0.3.dist-info/top_level.txt
DFA_visual_demo-1.0.3.dist-info/RECORD
